yet_another_json_config/__init__.py
yet_another_json_config/yet_another_json_config.py
yet_another_json_config-1.0.1.dist-info/LICENSE
yet_another_json_config-1.0.1.dist-info/METADATA
yet_another_json_config-1.0.1.dist-info/WHEEL
yet_another_json_config-1.0.1.dist-info/top_level.txt
yet_another_json_config-1.0.1.dist-info/RECORD
