Metadata-Version: 2.1
Name: yet-another-json-config
Version: 1.0.1
Summary: Reads and write json files as a configuration file, supports nested json values.
Author-email: engmtcdrm <gabif54409@rolenot.com>
Project-URL: Homepage, https://github.com/engmtcdrm/yet-another-json-config
Project-URL: Bug Tracker, https://github.com/engmtcdrm/yet-another-json-config/issues
Classifier: Programming Language :: Python :: 3
Classifier: License :: OSI Approved :: MIT License
Classifier: Operating System :: OS Independent
Requires-Python: >=3.6
License-File: LICENSE
